adversarial_robustness_toolbox-1.20.0.dist-info/licenses/AUTHORS
adversarial_robustness_toolbox-1.20.0.dist-info/licenses/LICENSE
art/__init__.py
art/config.py
art/data_generators.py
art/exceptions.py
art/optimizers.py
art/summary_writer.py
art/utils.py
art/visualization.py
art/attacks/__init__.py
art/attacks/attack.py
art/attacks/evasion/__init__.py
art/attacks/evasion/adversarial_asr.py
art/attacks/evasion/auto_attack.py
art/attacks/evasion/auto_conjugate_gradient.py
art/attacks/evasion/auto_projected_gradient_descent.py
art/attacks/evasion/boundary.py
art/attacks/evasion/brendel_bethge.py
art/attacks/evasion/carlini.py
art/attacks/evasion/composite_adversarial_attack.py
art/attacks/evasion/decision_tree_attack.py
art/attacks/evasion/deepfool.py
art/attacks/evasion/dpatch.py
art/attacks/evasion/dpatch_robust.py
art/attacks/evasion/elastic_net.py
art/attacks/evasion/fast_gradient.py
art/attacks/evasion/frame_saliency.py
art/attacks/evasion/geometric_decision_based_attack.py
art/attacks/evasion/hclu.py
art/attacks/evasion/hop_skip_jump.py
art/attacks/evasion/iterative_method.py
art/attacks/evasion/lowprofool.py
art/attacks/evasion/momentum_iterative_method.py
art/attacks/evasion/newtonfool.py
art/attacks/evasion/pe_malware_attack.py
art/attacks/evasion/pixel_threshold.py
art/attacks/evasion/rescaling_auto_conjugate_gradient.py
art/attacks/evasion/saliency_map.py
art/attacks/evasion/shadow_attack.py
art/attacks/evasion/sign_opt.py
art/attacks/evasion/simba.py
art/attacks/evasion/spatial_transformation.py
art/attacks/evasion/square_attack.py
art/attacks/evasion/targeted_universal_perturbation.py
art/attacks/evasion/universal_perturbation.py
art/attacks/evasion/virtual_adversarial.py
art/attacks/evasion/wasserstein.py
art/attacks/evasion/zoo.py
art/attacks/evasion/adversarial_patch/__init__.py
art/attacks/evasion/adversarial_patch/adversarial_patch.py
art/attacks/evasion/adversarial_patch/adversarial_patch_numpy.py
art/attacks/evasion/adversarial_patch/adversarial_patch_pytorch.py
art/attacks/evasion/adversarial_patch/adversarial_patch_tensorflow.py
art/attacks/evasion/adversarial_patch/utils.py
adversarial_robustness_toolbox-1.20.0.dist-info/METADATA
adversarial_robustness_toolbox-1.20.0.dist-info/WHEEL
adversarial_robustness_toolbox-1.20.0.dist-info/top_level.txt
adversarial_robustness_toolbox-1.20.0.dist-info/RECORD
